wme/__init__.py
wme/auth.py
wme/login_cli.py
wme/on_demand.py
wme/py.typed
wme-0.1.4.dist-info/LICENSE
wme-0.1.4.dist-info/METADATA
wme-0.1.4.dist-info/WHEEL
wme-0.1.4.dist-info/entry_points.txt
wme-0.1.4.dist-info/RECORD
