Metadata-Version: 2.3
Name: wme
Version: 0.1.4
Summary: python library for accessing the Wikimedia Enterprise API
License: MIT
Keywords: wikimedia,api,python
Author: Daniel Erenrich
Author-email: derenrich@wikimedia.org
Requires-Python: >=3.11,<4.0
Classifier: Development Status :: 4 - Beta
Classifier: Intended Audience :: Developers
Classifier: License :: OSI Approved :: MIT License
Classifier: Programming Language :: Python :: 3
Classifier: Programming Language :: Python :: 3.11
Classifier: Topic :: Software Development :: Libraries :: Python Modules
Requires-Dist: httpx (>=0,<1)
Requires-Dist: pydantic (>=2.7,<3.0)
